{
  "type": "footer",
  "name": "Footer group",
  "sections": {
    "footer": {
      "type": "footer",
      "blocks": {
        "links_BarQan": {
          "type": "links",
          "settings": {
            "menu": "footer"
          }
        }
      },
      "block_order": [
        "links_BarQan"
      ],
      "settings": {
        "logo": "shopify:\/\/shop_images\/Docs2Day_logo.svg",
        "logo_max_width": 80,
        "mobile_logo_max_width": 80,
        "show_social_media": true,
        "enable_follow_on_shop": false,
        "show_payment_icons": false,
        "show_locale_selector": false,
        "show_country_selector": false
      }
    }
  },
  "order": [
    "footer"
  ]
}
